basicldap3/__init__.py
basicldap3-0.1.2.dist-info/WHEEL
basicldap3-0.1.2.dist-info/METADATA
basicldap3-0.1.2.dist-info/RECORD
