Metadata-Version: 2.1
Name: basicldap3
Version: 0.1.2
Summary: Provides basic authentication using the ldap3 library
License: MIT
Author: Ramon Brandt
Author-email: devramon22@gmail.com
Requires-Python: >=3.6,<4.0
Classifier: License :: OSI Approved :: MIT License
Classifier: Programming Language :: Python :: 3
Classifier: Programming Language :: Python :: 3.6
Classifier: Programming Language :: Python :: 3.7
Classifier: Programming Language :: Python :: 3.8
Requires-Dist: ldap3 (>=2.6.1,<3.0.0)
